connio/__init__.py
connio/compat.py
connio/mqtt.py
connio/request_validator.py
connio/base/__init__.py
connio/base/deserialize.py
connio/base/domain.py
connio/base/exceptions.py
connio/base/instance_context.py
connio/base/instance_resource.py
connio/base/list_resource.py
connio/base/obsolete.py
connio/base/page.py
connio/base/serialize.py
connio/base/values.py
connio/base/version.py
connio/http/__init__.py
connio/http/http_client.py
connio/http/request.py
connio/http/response.py
connio/http/validation_client.py
connio/rest/__init__.py
connio/rest/api/__init__.py
connio/rest/api/v3/__init__.py
connio/rest/api/v3/account/__init__.py
connio/rest/api/v3/account/alert.py
connio/rest/api/v3/account/apiclient.py
connio/rest/api/v3/account/apikey.py
connio/rest/api/v3/account/app.py
connio/rest/api/v3/account/appprofile.py
connio/rest/api/v3/account/dataconnector.py
connio/rest/api/v3/account/device.py
connio/rest/api/v3/account/deviceprofile.py
connio/rest/api/v3/account/globals.py
connio/rest/api/v3/account/method.py
connio/rest/api/v3/account/propertyy.py
connio/rest/api/v3/account/user.py
connio/rest/api/v3/helpers/__init__.py
connio/rest/api/v3/sysuser/__init__.py
conniosdk-0.44.dist-info/METADATA
conniosdk-0.44.dist-info/WHEEL
conniosdk-0.44.dist-info/top_level.txt
conniosdk-0.44.dist-info/RECORD
