Metadata-Version: 2.1
Name: conniosdk
Version: 0.44
Summary: Connio Python SDK
Author-email: admin@digiterra.com.tr
Requires-Dist: six
Requires-Dist: requests
Requires-Dist: paho-mqtt
Requires-Dist: simplejson
